{
 "ksocha_ephysOptoStimulation": "ephys_passive_opto",
 "ksocha_ephysOptoChoiceWorld": "ephys_biased_opto",
 "passiveChoiceWorld": "ephys_replay",
 "opto_ephysChoiceWorld": "ephys_biased_opto",
 "ephysChoiceWorld": "ephys",
 "ephyskarolinaChoiceWorld": "ephys_biased_opto",
 "trainingChoiceWorldWidefield": "ephys_training",
 "passive_opto": "ephys",
 "widefieldChoiceWorld": "ephys_biased_opto",
 "opto_biasedChoiceWorld": "biased_opto",
 "opto_biased_ChoiceWorld": "biased_opto",
 "optoChoiceWorld": "biased_opto",
 "_biasedChoiceWorld": "biased",
 "biasedScanningChoiceWorld": "biased",
 "biasedVisOffChoiceWorld": "biased",
 "karolinaChoiceWorld": "biased_opto",
 "_habituationChoiceWorld": "habituation",
 "_trainingChoiceWorld": "training",
 "ephysMockChoiceWorld": "mock_ephys",
 "ephys_certification": "sync_ephys"
}
